goodlibs/__init__.py
goodlibs/cli.py
goodlibs/goodreads/__init__.py
goodlibs/goodreads/book.py
goodlibs/libgen/__init__.py
goodlibs/libgen/downloaders.py
goodlibs/libgen/exceptions.py
goodlibs/libgen/mirrors.py
goodlibs/libgen/publication.py
goodlibs/libgen/utils.py
goodlibs-0.1.1.dist-info/LICENSE
goodlibs-0.1.1.dist-info/METADATA
goodlibs-0.1.1.dist-info/WHEEL
goodlibs-0.1.1.dist-info/entry_points.txt
goodlibs-0.1.1.dist-info/top_level.txt
goodlibs-0.1.1.dist-info/RECORD
