Metadata-Version: 2.1
Name: goodlibs
Version: 0.1.1
Summary: Download books from a Goodreads shelf using Library Genesis.
Home-page: https://github.com/goodlibs/goodlibs
Author: goodlibs
Author-email: hello@goodlibs.com
License: UNKNOWN
Platform: UNKNOWN
Classifier: Programming Language :: Python :: 3.7
Classifier: Programming Language :: Python :: 3.8
Classifier: Development Status :: 4 - Beta
Classifier: Natural Language :: English
Classifier: License :: OSI Approved :: GNU General Public License v3 (GPLv3)
Classifier: Topic :: Utilities
Classifier: Intended Audience :: End Users/Desktop
Requires-Dist: beautifulsoup4
Requires-Dist: betterreads
Requires-Dist: click
Requires-Dist: fuzzywuzzy
Requires-Dist: requests
Requires-Dist: python-Levenshtein
Requires-Dist: Unidecode
